configureme/__init__.py
configureme/__version__.py
configureme/core.py
configureme/helpers.py
configureme-0.1.2a0.dist-info/AUTHORS.md
configureme-0.1.2a0.dist-info/LICENSE
configureme-0.1.2a0.dist-info/METADATA
configureme-0.1.2a0.dist-info/WHEEL
configureme-0.1.2a0.dist-info/top_level.txt
configureme-0.1.2a0.dist-info/RECORD
