Metadata-Version: 2.1
Name: configureme
Version: 0.1.2a0
Summary: Set up configuration for your application or library with ease.
Home-page: https://github.com/bradleygolden/configureme
Author: Bradley Golden
Author-email: golden.bradley@gmail.com
License: MIT
Platform: UNKNOWN
Classifier: License :: OSI Approved :: MIT License
Classifier: Programming Language :: Python
Classifier: Programming Language :: Python :: 3
Classifier: Programming Language :: Python :: 3.6
Requires-Python: >=3.6.0
